smartpy/__init__.py
smartpy/config.py
smartpy/environment.py
smartpy/libgmp.dylib
smartpy/metadata.py
smartpy/modules.py
smartpy/scenario_utils.py
smartpy/services.py
smartpy/sexp.py
smartpy/smartpy-canopy-linux.exe
smartpy/smartpy-canopy-macOS.exe
smartpy/smartpy-docker
smartpy/smartpy-oasis-linux.exe
smartpy/smartpy-oasis-macOS.exe
smartpy/state.py
smartpy/stdlib/address_utils.spy
smartpy/stdlib/fixed_point.spy
smartpy/stdlib/list_utils.spy
smartpy/stdlib/math.spy
smartpy/stdlib/rational.spy
smartpy/stdlib/statistics.spy
smartpy/stdlib/string_utils.spy
smartpy/stdlib/utils.spy
smartpy/syntax.py
smartpy/templates/admin_hand_over.py
smartpy/templates/admin_multisig.py
smartpy/templates/atomicSwap.py
smartpy/templates/baking_swap.py
smartpy/templates/bls12_381.py
smartpy/templates/bridge.py
smartpy/templates/calculator.py
smartpy/templates/calculator_main.spy
smartpy/templates/calculator_new.py
smartpy/templates/chain_id.py
smartpy/templates/check_dfs.py
smartpy/templates/chess.py
smartpy/templates/chess_test_3_repeat.py
smartpy/templates/chess_test_checkmate.py
smartpy/templates/chess_test_game1.py
smartpy/templates/chess_test_game2.py
smartpy/templates/collatz.py
smartpy/templates/contract_metadata.py
smartpy/templates/create_contract.py
smartpy/templates/effectful_apply.py
smartpy/templates/escrow.py
smartpy/templates/events.py
smartpy/templates/example_cyclic1.spy
smartpy/templates/example_cyclic2.spy
smartpy/templates/example_cyclic3.spy
smartpy/templates/example_import.spy
smartpy/templates/fa1_2.py
smartpy/templates/fa2_1_lib.py
smartpy/templates/fa2_1_lib_test_fungible.py
smartpy/templates/fa2_1_lib_test_nft.py
smartpy/templates/fa2_1_lib_test_single_asset.py
smartpy/templates/fa2_fungible_minimal.py
smartpy/templates/fa2_lib.py
smartpy/templates/fa2_lib_fungible.py
smartpy/templates/fa2_lib_nft.py
smartpy/templates/fa2_lib_single_asset.py
smartpy/templates/fa2_lib_test_fungible.py
smartpy/templates/fa2_lib_test_nft.py
tezos_smartpy-0.22.0.dist-info/LICENSE
tezos_smartpy-0.22.0.dist-info/METADATA
tezos_smartpy-0.22.0.dist-info/WHEEL
tezos_smartpy-0.22.0.dist-info/RECORD
