Metadata-Version: 2.1
Name: tezos-smartpy
Version: 0.22.0
Summary: A comprehensive solution for developing, testing, and deploying smart contracts on the Tezos blockchain.
Author: The SmartPy Team
Requires-Python: >=3.10,<4.0
Classifier: Programming Language :: Python :: 3
Classifier: Programming Language :: Python :: 3.10
Classifier: Programming Language :: Python :: 3.11
Requires-Dist: requests (>=2.25.1,<3.0.0)
